CHANGES.txt
README.txt
bootstrap.py
buildout.cfg
setup.py
src/zope/__init__.py
src/zope.app.ftp.egg-info/PKG-INFO
src/zope.app.ftp.egg-info/SOURCES.txt
src/zope.app.ftp.egg-info/dependency_links.txt
src/zope.app.ftp.egg-info/namespace_packages.txt
src/zope.app.ftp.egg-info/not-zip-safe
src/zope.app.ftp.egg-info/requires.txt
src/zope.app.ftp.egg-info/top_level.txt
src/zope/app/__init__.py
src/zope/app/ftp/README.txt
src/zope/app/ftp/SETUP.cfg
src/zope/app/ftp/__init__.py
src/zope/app/ftp/configure.zcml
src/zope/app/ftp/ftp-configure.zcml
src/zope/app/ftp/tests/__init__.py
src/zope/app/ftp/tests/demofs.py
src/zope/app/ftp/tests/test_ftpview.py